{
  "years": [
    {
      "year": 2025,
      "coverImage": "https://image-cdn-ak.spotifycdn.com/image/ab67706c0000da8466d8e4ed90c88053dc47eaa1",
      "enabled": true,
      "playlists": {
        "spotify": {
          "embed": "<iframe data-testid=\"embed-iframe\" style=\"border-radius:12px\" src=\"https://open.spotify.com/embed/playlist/32gNZnWdi67mMKmOo60YfV?utm_source=generator\" width=\"100%\" height=\"352\" frameBorder=\"0\" allowfullscreen=\"\" allow=\"autoplay; clipboard-write; encrypted-media; fullscreen; picture-in-picture\" loading=\"lazy\"></iframe>"
        },
        "youtube": {
          "embed": "<iframe width=\"560\" height=\"315\" src=\"https://www.youtube.com/embed/QuvqzlxEO6g?si=X7pgxx-4blWyo1-G\" title=\"YouTube video player\" frameborder=\"0\" allow=\"accelerometer; autoplay; clipboard-write; encrypted-media; gyroscope; picture-in-picture; web-share\" referrerpolicy=\"strict-origin-when-cross-origin\" allowfullscreen></iframe>"
        }
      }
    },
    {
      "year": 2024,
      "coverImage": "https://image-cdn-ak.spotifycdn.com/image/ab67706c0000da843d9bc4370e31c1a8822f5352",
      "enabled": true,
      "playlists": {
        "spotify": {
          "embed": "<iframe data-testid=\"embed-iframe\" style=\"border-radius:12px\" src=\"https://open.spotify.com/embed/playlist/0pqyzLEpqtt1AzHB0RGdvQ?utm_source=generator\" width=\"100%\" height=\"352\" frameBorder=\"0\" allowfullscreen=\"\" allow=\"autoplay; clipboard-write; encrypted-media; fullscreen; picture-in-picture\" loading=\"lazy\"></iframe>"
        }
      }
    },
    {
      "year": 2023,
      "coverImage": "https://image-cdn-fa.spotifycdn.com/image/ab67706c0000da84b8e462ab818aa4a5cac39e5a",
      "enabled": true,
      "playlists": {
        "spotify": {
          "embed": "<iframe data-testid=\"embed-iframe\" style=\"border-radius:12px\" src=\"https://open.spotify.com/embed/playlist/7xQIQYZZJ6Eu4SFbO0x64A?utm_source=generator\" width=\"100%\" height=\"352\" frameBorder=\"0\" allowfullscreen=\"\" allow=\"autoplay; clipboard-write; encrypted-media; fullscreen; picture-in-picture\" loading=\"lazy\"></iframe>"
        }
      }
    },
    {
      "year": 2022,
      "coverImage": "https://mosaic.scdn.co/640/ab67616d00001e0234bcf8eb3912d9f2312d6232ab67616d00001e027b107c478f006855e81af6b9ab67616d00001e028d364fc5e020e35bd1e4a57bab67616d00001e0290e72fba2f3f0f9889091c15",
      "enabled": true,
      "playlists": {
        "spotify": {
          "embed": "<iframe data-testid=\"embed-iframe\" style=\"border-radius:12px\" src=\"https://open.spotify.com/embed/playlist/6aOFbZYZTUO1qzsp5JS9v4?utm_source=generator\" width=\"100%\" height=\"352\" frameBorder=\"0\" allowfullscreen=\"\" allow=\"autoplay; clipboard-write; encrypted-media; fullscreen; picture-in-picture\" loading=\"lazy\"></iframe>"
        }
      }
    }
  ]
}

